{
  "repo_name": "ronniross/asi-dynamic-core",
  "last_updated": "2026-02-07T01:08:05.262291+00:00",
  "total_days_tracked": 5,
  "total_clones": 4,
  "max_unique_cloners_in_window": 2,
  "first_tracked": "2026-02-03",
  "last_tracked": "2026-02-07",
  "daily_history": [
    {
      "date": "2026-02-03",
      "clones": 0,
      "unique_cloners": 0
    },
    {
      "date": "2026-02-04",
      "clones": 1,
      "unique_cloners": 1
    },
    {
      "date": "2026-02-05",
      "clones": 1,
      "unique_cloners": 1
    },
    {
      "date": "2026-02-06",
      "clones": 0,
      "unique_cloners": 0
    },
    {
      "date": "2026-02-07",
      "clones": 2,
      "unique_cloners": 2
    }
  ]
}